jorgesomas5/__init__.py
jorgesomas5/soma.py
jorgesomas5-0.1.dist-info/LICENSE
jorgesomas5-0.1.dist-info/METADATA
jorgesomas5-0.1.dist-info/WHEEL
jorgesomas5-0.1.dist-info/top_level.txt
jorgesomas5-0.1.dist-info/RECORD
